rankfields-0.1.2.3.data/scripts/rankfields
ranking_phase_fields/__init__.py
ranking_phase_fields/__main__.py
ranking_phase_fields/features.py
ranking_phase_fields/generate_study.py
ranking_phase_fields/icsd2017
ranking_phase_fields/models.py
ranking_phase_fields/parse_icsd.py
ranking_phase_fields/rpp.input
ranking_phase_fields/symbols.py
ranking_phase_fields/symbols_noradio.py
ranking_phase_fields/train_and_validate.py
ranking_phase_fields/TABLES/AtomicVolume.table
ranking_phase_fields/TABLES/AtomicWeight.table
ranking_phase_fields/TABLES/BCCbandgap.table
ranking_phase_fields/TABLES/BCCefflatcnt.table
ranking_phase_fields/TABLES/BCCenergy_pa.table
ranking_phase_fields/TABLES/BCCenergydiff.table
ranking_phase_fields/TABLES/BCCfermi.table
ranking_phase_fields/TABLES/BCCmagmom.table
ranking_phase_fields/TABLES/BCCvolume_pa.table
ranking_phase_fields/TABLES/BCCvolume_padiff.table
ranking_phase_fields/TABLES/BoilingT.table
ranking_phase_fields/TABLES/Column.table
ranking_phase_fields/TABLES/CovalentRadius.table
ranking_phase_fields/TABLES/Density.table
ranking_phase_fields/TABLES/Electronegativity.table
ranking_phase_fields/TABLES/FirstIonizationEnergy.table
ranking_phase_fields/TABLES/GSbandgap.table
ranking_phase_fields/TABLES/GSefflatcnt.table
ranking_phase_fields/TABLES/GSenergy_pa.table
ranking_phase_fields/TABLES/GSestBCClatcnt.table
ranking_phase_fields/TABLES/GSestFCClatcnt.table
ranking_phase_fields/TABLES/GSmagmom.table
ranking_phase_fields/TABLES/GSvolume_pa.table
ranking_phase_fields/TABLES/ICSDVolume.table
ranking_phase_fields/TABLES/MeltingT.table
ranking_phase_fields/TABLES/MendeleevNumber.table
ranking_phase_fields/TABLES/MiracleRadius.table
ranking_phase_fields/TABLES/NUnfilled.table
ranking_phase_fields/TABLES/NValance.table
ranking_phase_fields/TABLES/NdUnfilled.table
ranking_phase_fields/TABLES/NdValence.table
ranking_phase_fields/TABLES/NfUnfilled.table
ranking_phase_fields/TABLES/NfValence.table
ranking_phase_fields/TABLES/NpUnfilled.table
rankfields-0.1.2.3.dist-info/LICENSE
rankfields-0.1.2.3.dist-info/METADATA
rankfields-0.1.2.3.dist-info/WHEEL
rankfields-0.1.2.3.dist-info/entry_points.txt
rankfields-0.1.2.3.dist-info/top_level.txt
rankfields-0.1.2.3.dist-info/RECORD
