Metadata-Version: 2.1
Name: rankfields
Version: 0.1.2.3
Summary: Ranking phase fields with likelihood of finding a stable composition
Home-page: http://github.com/lrcfmd/RankingPhaseFields
Author: Andrij Vasylenko
Author-email: and.vasylenko@gmail.com
License: MIT
Platform: UNKNOWN
Requires-Python: >=3.7, <3.9
Requires-Dist: pyod
Requires-Dist: numpy
Requires-Dist: tensorflow
Requires-Dist: scikit-learn (==0.20.0)
